similaritytoolbox/__about__.py
similaritytoolbox/__init__.py
similaritytoolbox/toolbox.py
similaritytoolbox-0.0.3.dist-info/METADATA
similaritytoolbox-0.0.3.dist-info/WHEEL
similaritytoolbox-0.0.3.dist-info/top_level.txt
similaritytoolbox-0.0.3.dist-info/RECORD
